{"nodes": [{"id": "frontend_src_pages_onboardingpage_tsx", "label": "OnboardingPage.tsx", "file_type": "code", "source_file": "frontend\\src\\pages\\OnboardingPage.tsx", "source_location": "L1"}, {"id": "onboardingpage_trimnull", "label": "trimNull()", "file_type": "code", "source_file": "frontend\\src\\pages\\OnboardingPage.tsx", "source_location": "L12"}, {"id": "onboardingpage_fn", "label": "fn()", "file_type": "code", "source_file": "frontend\\src\\pages\\OnboardingPage.tsx", "source_location": "L38"}, {"id": "onboardingpage_handleextract", "label": "handleExtract()", "file_type": "code", "source_file": "frontend\\src\\pages\\OnboardingPage.tsx", "source_location": "L265"}, {"id": "onboardingpage_handlecomplete", "label": "handleComplete()", "file_type": "code", "source_file": "frontend\\src\\pages\\OnboardingPage.tsx", "source_location": "L287"}], "edges": [{"source": "frontend_src_pages_onboardingpage_tsx", "target": "react", "relation": "imports_from", "confidence": "EXTRACTED", "source_file": "frontend\\src\\pages\\OnboardingPage.tsx", "source_location": "L1", "weight": 1.0}, {"source": "frontend_src_pages_onboardingpage_tsx", "target": "react_router_dom", "relation": "imports_from", "confidence": "EXTRACTED", "source_file": "frontend\\src\\pages\\OnboardingPage.tsx", "source_location": "L2", "weight": 1.0}, {"source": "frontend_src_pages_onboardingpage_tsx", "target": "frontend_src_lib_api", "relation": "imports_from", "confidence": "EXTRACTED", "source_file": "frontend\\src\\pages\\OnboardingPage.tsx", "source_location": "L3", "weight": 1.0}, {"source": "frontend_src_pages_onboardingpage_tsx", "target": "frontend_src_lib_session", "relation": "imports_from", "confidence": "EXTRACTED", "source_file": "frontend\\src\\pages\\OnboardingPage.tsx", "source_location": "L10", "weight": 1.0}, {"source": "frontend_src_pages_onboardingpage_tsx", "target": "onboardingpage_trimnull", "relation": "contains", "confidence": "EXTRACTED", "source_file": "frontend\\src\\pages\\OnboardingPage.tsx", "source_location": "L12", "weight": 1.0}, {"source": "frontend_src_pages_onboardingpage_tsx", "target": "onboardingpage_fn", "relation": "contains", "confidence": "EXTRACTED", "source_file": "frontend\\src\\pages\\OnboardingPage.tsx", "source_location": "L38", "weight": 1.0}, {"source": "frontend_src_pages_onboardingpage_tsx", "target": "onboardingpage_handleextract", "relation": "contains", "confidence": "EXTRACTED", "source_file": "frontend\\src\\pages\\OnboardingPage.tsx", "source_location": "L265", "weight": 1.0}, {"source": "frontend_src_pages_onboardingpage_tsx", "target": "onboardingpage_handlecomplete", "relation": "contains", "confidence": "EXTRACTED", "source_file": "frontend\\src\\pages\\OnboardingPage.tsx", "source_location": "L287", "weight": 1.0}, {"source": "onboardingpage_handlecomplete", "target": "onboardingpage_trimnull", "relation": "calls", "confidence": "EXTRACTED", "source_file": "frontend\\src\\pages\\OnboardingPage.tsx", "source_location": "L295", "weight": 1.0}], "raw_calls": [{"caller_nid": "onboardingpage_trimnull", "callee": "trim", "source_file": "frontend\\src\\pages\\OnboardingPage.tsx", "source_location": "L12"}, {"caller_nid": "onboardingpage_fn", "callee": "onClose", "source_file": "frontend\\src\\pages\\OnboardingPage.tsx", "source_location": "L38"}, {"caller_nid": "onboardingpage_handleextract", "callee": "trim", "source_file": "frontend\\src\\pages\\OnboardingPage.tsx", "source_location": "L266"}, {"caller_nid": "onboardingpage_handleextract", "callee": "setExtracting", "source_file": "frontend\\src\\pages\\OnboardingPage.tsx", "source_location": "L268"}, {"caller_nid": "onboardingpage_handleextract", "callee": "setError", "source_file": "frontend\\src\\pages\\OnboardingPage.tsx", "source_location": "L268"}, {"caller_nid": "onboardingpage_handleextract", "callee": "setSuccess", "source_file": "frontend\\src\\pages\\OnboardingPage.tsx", "source_location": "L268"}, {"caller_nid": "onboardingpage_handleextract", "callee": "extractUpworkProfile", "source_file": "frontend\\src\\pages\\OnboardingPage.tsx", "source_location": "L270"}, {"caller_nid": "onboardingpage_handleextract", "callee": "setProfileUrl", "source_file": "frontend\\src\\pages\\OnboardingPage.tsx", "source_location": "L272"}, {"caller_nid": "onboardingpage_handleextract", "callee": "setProfileId", "source_file": "frontend\\src\\pages\\OnboardingPage.tsx", "source_location": "L273"}, {"caller_nid": "onboardingpage_handleextract", "callee": "setProfileMarkdown", "source_file": "frontend\\src\\pages\\OnboardingPage.tsx", "source_location": "L274"}, {"caller_nid": "onboardingpage_handleextract", "callee": "setSuccess", "source_file": "frontend\\src\\pages\\OnboardingPage.tsx", "source_location": "L276"}, {"caller_nid": "onboardingpage_handleextract", "callee": "setError", "source_file": "frontend\\src\\pages\\OnboardingPage.tsx", "source_location": "L278"}, {"caller_nid": "onboardingpage_handleextract", "callee": "setError", "source_file": "frontend\\src\\pages\\OnboardingPage.tsx", "source_location": "L281"}, {"caller_nid": "onboardingpage_handleextract", "callee": "setExtracting", "source_file": "frontend\\src\\pages\\OnboardingPage.tsx", "source_location": "L283"}, {"caller_nid": "onboardingpage_handlecomplete", "callee": "trim", "source_file": "frontend\\src\\pages\\OnboardingPage.tsx", "source_location": "L288"}, {"caller_nid": "onboardingpage_handlecomplete", "callee": "setError", "source_file": "frontend\\src\\pages\\OnboardingPage.tsx", "source_location": "L289"}, {"caller_nid": "onboardingpage_handlecomplete", "callee": "setBusy", "source_file": "frontend\\src\\pages\\OnboardingPage.tsx", "source_location": "L292"}, {"caller_nid": "onboardingpage_handlecomplete", "callee": "setError", "source_file": "frontend\\src\\pages\\OnboardingPage.tsx", "source_location": "L292"}, {"caller_nid": "onboardingpage_handlecomplete", "callee": "setSuccess", "source_file": "frontend\\src\\pages\\OnboardingPage.tsx", "source_location": "L292"}, {"caller_nid": "onboardingpage_handlecomplete", "callee": "createProfile", "source_file": "frontend\\src\\pages\\OnboardingPage.tsx", "source_location": "L294"}, {"caller_nid": "onboardingpage_handlecomplete", "callee": "markProfileHint", "source_file": "frontend\\src\\pages\\OnboardingPage.tsx", "source_location": "L300"}, {"caller_nid": "onboardingpage_handlecomplete", "callee": "markSessionHint", "source_file": "frontend\\src\\pages\\OnboardingPage.tsx", "source_location": "L301"}, {"caller_nid": "onboardingpage_handlecomplete", "callee": "navigate", "source_file": "frontend\\src\\pages\\OnboardingPage.tsx", "source_location": "L302"}, {"caller_nid": "onboardingpage_handlecomplete", "callee": "setError", "source_file": "frontend\\src\\pages\\OnboardingPage.tsx", "source_location": "L304"}, {"caller_nid": "onboardingpage_handlecomplete", "callee": "setBusy", "source_file": "frontend\\src\\pages\\OnboardingPage.tsx", "source_location": "L306"}]}